cribl_control_plane/__init__.py
cribl_control_plane/_hooks/__init__.py
cribl_control_plane/_hooks/clientcredentials.py
cribl_control_plane/_hooks/registration.py
cribl_control_plane/_hooks/sdkhooks.py
cribl_control_plane/_hooks/types.py
cribl_control_plane/_version.py
cribl_control_plane/acl.py
cribl_control_plane/auth.py
cribl_control_plane/basesdk.py
cribl_control_plane/branches.py
cribl_control_plane/collectors_sdk.py
cribl_control_plane/commits.py
cribl_control_plane/configs_versions.py
cribl_control_plane/cribl.py
cribl_control_plane/destinations.py
cribl_control_plane/errors/__init__.py
cribl_control_plane/errors/apierror.py
cribl_control_plane/errors/criblcontrolplaneerror.py
cribl_control_plane/errors/error.py
cribl_control_plane/errors/healthserverstatus_error.py
cribl_control_plane/errors/no_response_error.py
cribl_control_plane/errors/responsevalidationerror.py
cribl_control_plane/files.py
cribl_control_plane/functions.py
cribl_control_plane/groups_configs.py
cribl_control_plane/groups_sdk.py
cribl_control_plane/health.py
cribl_control_plane/hectokens.py
cribl_control_plane/httpclient.py
cribl_control_plane/lakedatasets.py
cribl_control_plane/models/__init__.py
cribl_control_plane/models/acknowledgmentsoptions.py
cribl_control_plane/models/acknowledgmentsoptions1.py
cribl_control_plane/models/addhectokenrequest.py
cribl_control_plane/models/additionalpropertiestypejobinfostats.py
cribl_control_plane/models/additionalpropertiestypepipelineconfgroups.py
cribl_control_plane/models/apitypesystemsettingsconf.py
cribl_control_plane/models/authenticationmethodoptions.py
cribl_control_plane/models/authenticationmethodoptions1.py
cribl_control_plane/models/authenticationmethodoptions2.py
cribl_control_plane/models/authenticationmethodoptionsauth.py
cribl_control_plane/models/authenticationmethodoptionsauthtokensitems.py
cribl_control_plane/models/authenticationmethodoptionss3collectorconf.py
cribl_control_plane/models/authenticationmethodoptionssasl.py
cribl_control_plane-0.5.2.dist-info/METADATA
cribl_control_plane-0.5.2.dist-info/WHEEL
cribl_control_plane-0.5.2.dist-info/licenses/LICENSE
cribl_control_plane-0.5.2.dist-info/RECORD
